{"stats":{"minecraft:custom":{"minecraft:time_since_rest":43338,"minecraft:sprint_one_cm":23846,"minecraft:play_time":44586,"minecraft:deaths":1,"minecraft:walk_one_cm":138224,"minecraft:walk_under_water_one_cm":2790,"minecraft:mob_kills":2,"minecraft:drop":2,"minecraft:jump":193,"minecraft:damage_dealt":196,"minecraft:leave_game":3,"minecraft:walk_on_water_one_cm":1033,"minecraft:time_since_death":43297,"minecraft:total_world_time":44586,"minecraft:fly_one_cm":447073},"minecraft:dropped":{"minecraft:white_concrete":2},"minecraft:picked_up":{"minecraft:glow_ink_sac":4,"minecraft:leather":1,"minecraft:candle":1,"minecraft:beef":1,"minecraft:white_concrete":3,"minecraft:ink_sac":4,"minecraft:black_wool":1,"minecraft:mutton":8,"minecraft:white_wool":6},"minecraft:used":{"minecraft:white_wool":1,"minecraft:smooth_quartz_slab":10,"minecraft:black_stained_glass_pane":56,"minecraft:grass_block":20,"minecraft:spruce_planks":3,"minecraft:white_concrete":860,"minecraft:candle":2}},"DataVersion":2865}